jiav/__init__.py
jiav/backend.py
jiav/cli.py
jiav/content.py
jiav/exceptions.py
jiav/jira.py
jiav/logger.py
jiav/manifest.py
jiav/summary.py
jiav/verification.py
jiav_jira_issue/__init__.py
jiav_jira_issue/backend.py
jiav_jira_issue/py.typed
jiav_lineinfile/__init__.py
jiav_lineinfile/backend.py
jiav_lineinfile/py.typed
jiav_regexinfile/__init__.py
jiav_regexinfile/backend.py
jiav_regexinfile/py.typed
jiav-0.3.2.dist-info/LICENSE
jiav-0.3.2.dist-info/METADATA
jiav-0.3.2.dist-info/WHEEL
jiav-0.3.2.dist-info/entry_points.txt
jiav-0.3.2.dist-info/RECORD
