Metadata-Version: 2.1
Name: jiav
Version: 0.3.2
Summary: Jira Issues Auto Verification
Home-page: https://github.com/vkhitrin/jiav
License: BSD-3-Clause
Author: Vadim Khitrin
Author-email: me@vkhitrin.com
Requires-Python: >=3.8,<4.0
Classifier: Development Status :: 3 - Alpha
Classifier: Environment :: Console
Classifier: License :: OSI Approved :: BSD License
Classifier: Operating System :: MacOS
Classifier: Operating System :: POSIX :: Linux
Classifier: Programming Language :: Python :: 3
Classifier: Programming Language :: Python :: 3.8
Classifier: Programming Language :: Python :: 3.9
Classifier: Programming Language :: Python :: 3.10
Classifier: Programming Language :: Python :: 3.11
Classifier: Programming Language :: Python :: 3.12
Classifier: Programming Language :: Python :: 3 :: Only
Classifier: Topic :: Utilities
Requires-Dist: colorlog (>=6.7.0,<7.0.0)
Requires-Dist: importlib-metadata (>=8.2.0,<9.0.0)
Requires-Dist: iteration-utilities (>=0.12.1,<0.13.0)
Requires-Dist: jira (>=3.8.0,<4.0.0)
Requires-Dist: jsonschema (>=4.17.3,<5.0.0)
Requires-Dist: pyyaml (>=6.0,<7.0)
Requires-Dist: rich-click (>=1.8.3,<2.0.0)
Project-URL: Documentation, https://jiav.readthedocs.io
Project-URL: Repository, https://github.com/vkhitrin/jiav
